requestsH/__init__.py
requestsH/main.py
requestsH-0.1.dist-info/LICENSE
requestsH-0.1.dist-info/METADATA
requestsH-0.1.dist-info/WHEEL
requestsH-0.1.dist-info/top_level.txt
requestsH-0.1.dist-info/RECORD
