Metadata-Version: 2.1
Name: requestsH
Version: 0.1
Summary: Simplify the use of requests module
Home-page: https://www.hah3.com
Author: wuhahe
Author-email: 529516310@qq.com
License: UNKNOWN
Project-URL: Bug Tracker, https://www.hah3.com
Platform: UNKNOWN
Classifier: Programming Language :: Python :: 3
Classifier: License :: OSI Approved :: MIT License
Classifier: Operating System :: OS Independent
Requires-Python: >=3.8
License-File: LICENSE
